eldar_chainword/__init__.py
eldar_chainword/game.py
eldar_chainword/words.py
eldar_chainword-1.0.2.dist-info/METADATA
eldar_chainword-1.0.2.dist-info/WHEEL
eldar_chainword-1.0.2.dist-info/entry_points.txt
eldar_chainword-1.0.2.dist-info/top_level.txt
eldar_chainword-1.0.2.dist-info/RECORD
