Metadata-Version: 2.4
Name: eldar-chainword
Version: 1.0.2
Summary: CLI Chain Word Game (Şəhər-Şəhər style)
Author: Eldar
Requires-Python: >=3.8
